dhanuma_datainstinct/__init__.py
dhanuma_datainstinct/core.py
dhanuma_datainstinct/stats.py
dhanuma_datainstinct/utils.py
dhanuma_datainstinct-0.1.0.dist-info/METADATA
dhanuma_datainstinct-0.1.0.dist-info/WHEEL
dhanuma_datainstinct-0.1.0.dist-info/top_level.txt
dhanuma_datainstinct-0.1.0.dist-info/RECORD
